captchatools/__init__.py
captchatools/anticaptcha.py
captchatools/capmonster.py
captchatools/capsolver.py
captchatools/captchaai.py
captchatools/errors.py
captchatools/exceptions.py
captchatools/twocap.py
captchatools-1.5.0.dist-info/LICENSE
captchatools-1.5.0.dist-info/METADATA
captchatools-1.5.0.dist-info/WHEEL
captchatools-1.5.0.dist-info/top_level.txt
captchatools-1.5.0.dist-info/RECORD
