Metadata-Version: 2.1
Name: captchatools
Version: 1.5.0
Summary: Python module to help solve captchas with Capmonster, 2captcha and Anticaptcha API's!
Home-page: https://github.com/Matthew17-21/Captcha-Tools
Author: Matthew17-21
Author-email: admin@monumentalshopping.com
License: MIT
Keywords: captcha,2captcha,capmonster,anticaptcha,scraping,scrape,challenge,sneakers
Platform: UNKNOWN
Classifier: Intended Audience :: Developers
Classifier: Natural Language :: English
Classifier: Programming Language :: Python
Classifier: Programming Language :: Python :: 3
Classifier: Programming Language :: Python :: 3.6
Classifier: Programming Language :: Python :: 3.7
Classifier: Programming Language :: Python :: 3.8
Classifier: Programming Language :: Python :: 3.9
Classifier: Topic :: Internet :: WWW/HTTP
Classifier: Topic :: Software Development :: Libraries :: Python Modules
Requires-Dist: requests
